setup.py
sqlauthenticator/__init__.py
sqlauthenticator/sqlauthenticator.py
sqlauthenticator.egg-info/PKG-INFO
sqlauthenticator.egg-info/SOURCES.txt
sqlauthenticator.egg-info/dependency_links.txt
sqlauthenticator.egg-info/requires.txt
sqlauthenticator.egg-info/top_level.txt