Metadata-Version: 1.0
Name: sqlauthenticator
Version: 1.0
Summary: SQL Authenticator for Jupyterhub
Home-page: https://github.com/bcongdon/jupyterhub-sqlauthenticator
Author: Benjamin Congdon
Author-email: bcongdo2@illinois.edu
License: MIT
Platform: UNKNOWN
